jt-sdk/__init__.py
jt-sdk/__version__.py
jt-sdk/jtClient.py
jt-sdk/jtConstant.py
jt-sdk/jtException.py
jtSDK/__init__.py
jtSDK/__version__.py
jtSDK/jtClient.py
jtSDK/jtConstant.py
jtSDK/jtException.py
jtSDK-0.0.1.dist-info/METADATA
jtSDK-0.0.1.dist-info/RECORD
jtSDK-0.0.1.dist-info/WHEEL
jtSDK-0.0.1.dist-info/top_level.txt
